doti18n/__init__.py
doti18n/__main__.py
doti18n/errors.py
doti18n/locale_data.py
doti18n/locale_translator.py
doti18n/utils.py
doti18n/cli/__init__.py
doti18n/cli/commands/__init__.py
doti18n/cli/commands/lint/__init__.py
doti18n/cli/commands/lint/command.py
doti18n/cli/commands/lint/lint.py
doti18n/cli/commands/stub/__init__.py
doti18n/cli/commands/stub/command.py
doti18n/cli/commands/stub/formatted_stub.py
doti18n/cli/commands/stub/generate_code.py
doti18n/cli/commands/stub/icumf_stub.py
doti18n/cli/commands/stub/plural_stub.py
doti18n/icumf/__init__.py
doti18n/icumf/nodes.py
doti18n/icumf/parser.py
doti18n/icumf/formatters/__init__.py
doti18n/icumf/formatters/base.py
doti18n/icumf/formatters/count.py
doti18n/icumf/formatters/date.py
doti18n/icumf/formatters/html.py
doti18n/icumf/formatters/markdown.py
doti18n/icumf/formatters/plural.py
doti18n/icumf/formatters/select.py
doti18n/icumf/formatters/selectordinal.py
doti18n/loaders/__init__.py
doti18n/loaders/base_loader.py
doti18n/loaders/json_loader.py
doti18n/loaders/xml_loader.py
doti18n/loaders/yaml_loader.py
doti18n/wrapped/__init__.py
doti18n/wrapped/locale_list.py
doti18n/wrapped/locale_namespace.py
doti18n/wrapped/none_wrapper.py
doti18n/wrapped/plural_wrapper.py
doti18n/wrapped/string_wrapper.py
doti18n-0.6.0.dist-info/licenses/LICENSE
doti18n-0.6.0.dist-info/METADATA
doti18n-0.6.0.dist-info/WHEEL
doti18n-0.6.0.dist-info/entry_points.txt
doti18n-0.6.0.dist-info/top_level.txt
doti18n-0.6.0.dist-info/RECORD
