Metadata-Version: 2.4
Name: doti18n
Version: 0.6.0
Summary: Python library for loading localizations with dot access and pluralization.
Author-email: darkj3suss <asdzxco@protonmail.com>
License: MIT
Project-URL: Homepage, https://github.com/darkj3suss/doti18n
Project-URL: BugTracker, https://github.com/darkj3suss/doti18n/issues
Project-URL: Repository, https://github.com/darkj3suss/doti18n
Keywords: localization,i18n,l10n,translate,yaml,json,yml,text processing,dot access,pluralization,babel
Classifier: Programming Language :: Python :: 3
Classifier: Programming Language :: Python :: 3.11
Classifier: Programming Language :: Python :: 3.12
Classifier: Programming Language :: Python :: 3.13
Classifier: Operating System :: OS Independent
Classifier: Development Status :: 3 - Alpha
Classifier: Intended Audience :: Developers
Classifier: Topic :: Software Development :: Libraries :: Python Modules
Classifier: Topic :: Software Development :: Localization
Classifier: Topic :: Text Processing :: Linguistic
Requires-Python: >=3.11
License-File: LICENSE
Requires-Dist: babel>=2.17.0
Requires-Dist: colorlog>=6.7.0
Provides-Extra: yaml
Requires-Dist: PyYAML>=6.0; extra == "yaml"
Dynamic: license-file
